fastapi_admin_next/__init__.py
fastapi_admin_next/configs/__init__.py
fastapi_admin_next/configs/auth_config.py
fastapi_admin_next/constants.py
fastapi_admin_next/controllers/__init__.py
fastapi_admin_next/controllers/admin.py
fastapi_admin_next/controllers/auth.py
fastapi_admin_next/crud.py
fastapi_admin_next/db_connect.py
fastapi_admin_next/dependencies/__init__.py
fastapi_admin_next/dependencies/login.py
fastapi_admin_next/dependencies/query_param.py
fastapi_admin_next/error/__init__.py
fastapi_admin_next/error/exceptions.py
fastapi_admin_next/exceptions.py
fastapi_admin_next/jinja_filters.py
fastapi_admin_next/logger.py
fastapi_admin_next/main.py
fastapi_admin_next/middleware/__init__.py
fastapi_admin_next/middleware/error_handler.py
fastapi_admin_next/registry.py
fastapi_admin_next/router.py
fastapi_admin_next/schemas.py
fastapi_admin_next/security/__init__.py
fastapi_admin_next/security/backend.py
fastapi_admin_next/security/security.py
fastapi_admin_next/security/token_handler.py
fastapi_admin_next/services/__init__.py
fastapi_admin_next/services/admin.py
fastapi_admin_next/services/auth.py
fastapi_admin_next/services/base.py
fastapi_admin_next/static/css/styles.css
fastapi_admin_next/static/js/datatables-simple-demo.js
fastapi_admin_next/static/js/scripts.js
fastapi_admin_next/templates/auth/login.html
fastapi_admin_next/templates/base.html
fastapi_admin_next/templates/create.html
fastapi_admin_next/templates/delete.html
fastapi_admin_next/templates/index.html
fastapi_admin_next/templates/list.html
fastapi_admin_next/templates/partials/navbar.html
fastapi_admin_next/templates/partials/scripts.html
fastapi_admin_next/templates/partials/sidebar.html
fastapi_admin_next/templates/partials/styles.html
fastapi_admin_next/templates/update.html
fastapi_admin_next/validation.py
fastapi_admin_next-0.1.2.dist-info/LICENSE
fastapi_admin_next-0.1.2.dist-info/METADATA
fastapi_admin_next-0.1.2.dist-info/WHEEL
fastapi_admin_next-0.1.2.dist-info/RECORD
