Metadata-Version: 2.1
Name: fastapi-admin-next
Version: 0.1.2
Summary: 
Author: MahmudulHassan5809
Author-email: mahmudul.hassan240@gmail.com
Requires-Python: >=3.12,<4.0
Classifier: Programming Language :: Python :: 3
Classifier: Programming Language :: Python :: 3.12
Classifier: Programming Language :: Python :: 3.13
Requires-Dist: bcrypt (>=4.2.1,<5.0.0)
Requires-Dist: fastapi (>=0.115.6,<0.116.0)
Requires-Dist: itsdangerous (>=2.2.0,<3.0.0)
Requires-Dist: jinja2 (>=3.1.4,<4.0.0)
Requires-Dist: pydantic (>=2.10.3,<3.0.0)
Requires-Dist: python-jose[cryptography] (>=3.3.0,<4.0.0)
Requires-Dist: sqlalchemy (>=2.0.36,<3.0.0)
